goat_wallets/solana/__init__.py
goat_wallets/solana/send_sol.py
goat_wallets/solana/wallet.py
goat_sdk_wallet_solana-0.1.6.dist-info/METADATA
goat_sdk_wallet_solana-0.1.6.dist-info/WHEEL
goat_sdk_wallet_solana-0.1.6.dist-info/RECORD
