Metadata-Version: 2.1
Name: goat-sdk-wallet-solana
Version: 0.1.6
Summary: Goat SDK Solana wallet implementation
Home-page: https://ohmygoat.dev/
Keywords: goat,sdk,solana,agents,ai,wallet
Author: Andrea Villa
Author-email: andreakarimodm@gmail.com
Requires-Python: >=3.10,<4.0
Classifier: Programming Language :: Python :: 3
Classifier: Programming Language :: Python :: 3.10
Classifier: Programming Language :: Python :: 3.11
Classifier: Programming Language :: Python :: 3.12
Requires-Dist: PyNaCl (>=1.5.0,<2.0.0)
Requires-Dist: goat-sdk (>=0.1.0,<0.2.0)
Requires-Dist: solana (>=0.30.2)
Requires-Dist: solders (>=0.18.0)
Project-URL: Bug Tracker, https://github.com/goat-sdk/goat/issues
Project-URL: Repository, https://github.com/goat-sdk/goat
